wedata_pre_code/__init__.py
wedata_pre_code/client.py
wedata_pre_code/common/__init__.py
wedata_pre_code/common/base_client.py
wedata_pre_code/wedata2/__init__.py
wedata_pre_code/wedata2/client.py
wedata_pre_code/wedata3/__init__.py
wedata_pre_code/wedata3/client.py
wedata_pre_code-1.0.1.dist-info/METADATA
wedata_pre_code-1.0.1.dist-info/WHEEL
wedata_pre_code-1.0.1.dist-info/top_level.txt
wedata_pre_code-1.0.1.dist-info/RECORD
