Metadata-Version: 2.4
Name: wedata-pre-code
Version: 1.0.1
Summary: WeData平台的预执行代码库，为机器学习实验提供与MLflow的深度集成
Author-email: WeData Team <wedata@tencent.com>
License: MIT
Project-URL: Homepage, https://wedata.tencent.com
Project-URL: Documentation, https://wedata.tencent.com/docs
Classifier: Development Status :: 4 - Beta
Classifier: Intended Audience :: Developers
Classifier: License :: OSI Approved :: MIT License
Classifier: Programming Language :: Python :: 3
Classifier: Programming Language :: Python :: 3.8
Classifier: Programming Language :: Python :: 3.9
Classifier: Programming Language :: Python :: 3.10
Classifier: Programming Language :: Python :: 3.11
Classifier: Topic :: Scientific/Engineering :: Artificial Intelligence
Requires-Python: >=3.8
Requires-Dist: mlflow>=2.0.0
Provides-Extra: dev
Requires-Dist: pytest>=6.0.0; extra == "dev"
Requires-Dist: black>=21.0.0; extra == "dev"
Requires-Dist: flake8>=3.9.0; extra == "dev"
